sagepaypi/__init__.py
sagepaypi/admin.py
sagepaypi/conf.py
sagepaypi/constants.py
sagepaypi/exceptions.py
sagepaypi/fields.py
sagepaypi/gateway.py
sagepaypi/tokens.py
sagepaypi/urls.py
sagepaypi/widgets.py
sagepaypi/forms/__init__.py
sagepaypi/forms/card_identifier.py
sagepaypi/forms/transaction.py
sagepaypi/migrations/0001_initial.py
sagepaypi/migrations/0002_auto_20190309_0909.py
sagepaypi/migrations/0003_auto_20190312_1146.py
sagepaypi/migrations/__init__.py
sagepaypi/models/__init__.py
sagepaypi/models/card_identifier.py
sagepaypi/models/transaction.py
sagepaypi/templates/sagepaypi/3d_secure_redirect_form.html
sagepaypi/templates/sagepaypi/tags/3d_secure_redirect.html
sagepaypi/templatetags/__init__.py
sagepaypi/templatetags/sagepaypi_tags.py
sagepaypi/utils/__init__.py
sagepaypi/utils/version.py
sagepaypi/views/__init__.py
sagepaypi/views/transaction.py
django_sagepaypi-1.0.dist-info/LICENSE
django_sagepaypi-1.0.dist-info/METADATA
django_sagepaypi-1.0.dist-info/WHEEL
django_sagepaypi-1.0.dist-info/top_level.txt
django_sagepaypi-1.0.dist-info/RECORD
