Metadata-Version: 2.1
Name: django-sagepaypi
Version: 1.0
Summary: Django SagePayPI Payment Gateway
Home-page: https://github.com/AccentDesign/django-sagepaypi/
Author: Stuart George
Author-email: stuart@accentdesign.co.uk
License: MIT
Download-URL: https://pypi.python.org/pypi/django-sagepaypi
Keywords: django,sagepay,pi,payment,accent,design
Platform: UNKNOWN
Classifier: Development Status :: 5 - Production/Stable
Classifier: Intended Audience :: Developers
Classifier: License :: OSI Approved :: MIT License
Classifier: Operating System :: OS Independent
Classifier: Programming Language :: Python :: 3
Classifier: Programming Language :: Python :: 3.4
Classifier: Programming Language :: Python :: 3.5
Classifier: Programming Language :: Python :: 3.6
Classifier: Framework :: Django
Classifier: Framework :: Django :: 2.0
Classifier: Topic :: Internet :: WWW/HTTP :: Site Management
Requires-Dist: Django (>=2)
Requires-Dist: pycountry (>=18.12.8)
Requires-Dist: python-dateutil (>=2.6)
Requires-Dist: requests (>=2)
Provides-Extra: docs
Requires-Dist: sphinxcontrib-spelling (>=2.3.0) ; extra == 'docs'
Requires-Dist: Sphinx (>=1.5.2) ; extra == 'docs'
Requires-Dist: sphinx-autobuild (>=0.6.0) ; extra == 'docs'
Requires-Dist: karma-sphinx-theme (>=0.0.6) ; extra == 'docs'
Provides-Extra: tests
Requires-Dist: mock ; extra == 'tests'
Requires-Dist: pyyaml ; extra == 'tests'
